usda_fdc/__init__.py
usda_fdc/cli.py
usda_fdc/client.py
usda_fdc/exceptions.py
usda_fdc/models.py
usda_fdc/utils.py
usda_fdc/analysis/resources/dri/rda.json
usda_fdc/analysis/resources/dri/rda_female.json
usda_fdc/analysis/resources/dri/rda_male.json
usda_fdc/analysis/resources/dri/ul.json
usda_fdc-0.1.9.dist-info/licenses/LICENSE
usda_fdc-0.1.9.dist-info/METADATA
usda_fdc-0.1.9.dist-info/WHEEL
usda_fdc-0.1.9.dist-info/entry_points.txt
usda_fdc-0.1.9.dist-info/top_level.txt
usda_fdc-0.1.9.dist-info/RECORD
