Metadata-Version: 2.4
Name: usda_fdc
Version: 0.1.9
Summary: A comprehensive Python library for interacting with the USDA Food Data Central API
Author-email: Michael McGarrah <mcgarrah@gmail.com>
License: MIT
Project-URL: Homepage, https://github.com/mcgarrah/usda_fdc_python
Project-URL: Documentation, https://usda-fdc.readthedocs.io
Project-URL: Issues, https://github.com/mcgarrah/usda_fdc_python/issues
Classifier: Development Status :: 3 - Alpha
Classifier: Intended Audience :: Developers
Classifier: License :: OSI Approved :: MIT License
Classifier: Programming Language :: Python :: 3
Classifier: Programming Language :: Python :: 3.8
Classifier: Programming Language :: Python :: 3.9
Classifier: Programming Language :: Python :: 3.10
Classifier: Programming Language :: Python :: 3.11
Classifier: Topic :: Software Development :: Libraries :: Python Modules
Requires-Python: >=3.8
License-File: LICENSE
Requires-Dist: requests>=2.25.0
Requires-Dist: pint>=0.17
Requires-Dist: python-dotenv>=0.19.0
Provides-Extra: django
Requires-Dist: Django>=3.2; extra == "django"
Provides-Extra: dev
Requires-Dist: pytest>=6.0.0; extra == "dev"
Requires-Dist: pytest-cov>=2.12.0; extra == "dev"
Requires-Dist: black>=21.5b2; extra == "dev"
Requires-Dist: isort>=5.9.1; extra == "dev"
Requires-Dist: mypy>=0.812; extra == "dev"
Requires-Dist: flake8>=3.9.2; extra == "dev"
Provides-Extra: docs
Requires-Dist: sphinx>=4.0.2; extra == "docs"
Requires-Dist: sphinx-rtd-theme>=0.5.2; extra == "docs"
Dynamic: license-file
